data_quality_kit/__init__.py
data_quality_kit/accuracy.py
data_quality_kit/completeness.py
data_quality_kit/consistency.py
data_quality_kit/validity.py
tests/__init__.py
tests/global_test_data.py
tests/test_accuracy.py
tests/test_completeness.py
tests/test_consistency.py
tests/test_validity.py
data_quality_kit-0.8.0.dist-info/LICENSE
data_quality_kit-0.8.0.dist-info/METADATA
data_quality_kit-0.8.0.dist-info/WHEEL
data_quality_kit-0.8.0.dist-info/top_level.txt
data_quality_kit-0.8.0.dist-info/RECORD
