Metadata-Version: 2.1
Name: data-quality-kit
Version: 0.8.0
Summary: library of functions for managing and improving data quality in Datasets
Home-page: https://github.com/Dante33CTP/data-quality-kit
Author: DantePedrozo
Author-email: dante.victor.33@gmail.com
License: Apache License 2.0
Keywords: Data Quality
Classifier: License :: OSI Approved :: Apache Software License
Classifier: Topic :: Software Development :: Libraries :: Python Modules
Classifier: Programming Language :: Python
Classifier: Programming Language :: Python :: 2
Classifier: Programming Language :: Python :: 2.7
Classifier: Programming Language :: Python :: 3
Classifier: Programming Language :: Python :: 3.4
Classifier: Programming Language :: Python :: 3.5
Classifier: Programming Language :: Python :: 3.6
Classifier: Programming Language :: Python :: 3.7
Classifier: Programming Language :: Python :: 3.8
Classifier: Programming Language :: Python :: 3.9
Classifier: Programming Language :: Python :: 3.10
License-File: LICENSE
Requires-Dist: pandas>=2.2.2
Requires-Dist: assertpy>=1.1.0
Requires-Dist: pytest>=8.2.2
